{
    "rouge1": 1.43,
    "rouge2": 0.0,
    "rougeL": 1.43,
    "rougeLsum": 1.43,
    "R": 0.95,
    "gen_len": 1.0,
    "model_name": "microsoft/phi-2",
    "datetime": "2024-02-21T12:18:46.654482"
}{
    "rouge1": 1.43,
    "rouge2": 0.0,
    "rougeL": 1.43,
    "rougeLsum": 1.43,
    "R": 0.95,
    "gen_len": 1.0,
    "model_name": "microsoft/phi-2",
    "datetime": "2024-02-21T12:21:41.098708"
}{
    "rouge1": 1.43,
    "rouge2": 0.0,
    "rougeL": 1.43,
    "rougeLsum": 1.43,
    "R": 0.95,
    "gen_len": 1.0,
    "model_name": "microsoft/phi-2",
    "datetime": "2024-02-21T12:22:29.470263"
}{
    "rouge1": 5.09,
    "rouge2": 0.0,
    "rougeL": 5.09,
    "rougeLsum": 4.32,
    "R": 3.39,
    "gen_len": 1.0,
    "model_name": "microsoft/phi-2",
    "datetime": "2024-02-21T12:24:26.665905"
}{
    "rouge1": 2.08,
    "rouge2": 0.0,
    "rougeL": 2.08,
    "rougeLsum": 2.08,
    "R": 1.39,
    "gen_len": 1.0,
    "model_name": "microsoft/phi-2",
    "datetime": "2024-02-21T12:25:20.027149"
}{
    "rouge1": 7.78,
    "rouge2": 2.78,
    "rougeL": 7.78,
    "rougeLsum": 7.78,
    "R": 6.11,
    "gen_len": 1.0,
    "model_name": "microsoft/phi-2",
    "datetime": "2024-02-21T12:30:35.439595"
}{
    "rouge1": 7.63,
    "rouge2": 0.0,
    "rougeL": 6.92,
    "rougeLsum": 6.92,
    "R": 4.84,
    "gen_len": 1.0,
    "model_name": "microsoft/phi-2",
    "datetime": "2024-02-21T12:31:23.024518"
}{
    "rouge1": 7.78,
    "rouge2": 2.78,
    "rougeL": 7.78,
    "rougeLsum": 7.78,
    "R": 6.11,
    "gen_len": 1.0,
    "model_name": "microsoft/phi-2",
    "datetime": "2024-02-21T12:34:48.275907"
}{
    "rouge1": 7.78,
    "rouge2": 2.78,
    "rougeL": 7.78,
    "rougeLsum": 7.78,
    "R": 6.11,
    "gen_len": 1.0,
    "model_name": "microsoft/phi-2",
    "datetime": "2024-02-21T12:37:57.653649"
}{
    "rouge1": 7.63,
    "rouge2": 0.0,
    "rougeL": 6.92,
    "rougeLsum": 6.92,
    "R": 4.84,
    "gen_len": 1.0,
    "model_name": "microsoft/phi-2",
    "datetime": "2024-02-21T12:38:47.457951"
}{
    "rouge1": 7.78,
    "rouge2": 2.78,
    "rougeL": 7.78,
    "rougeLsum": 7.78,
    "R": 6.11,
    "gen_len": 1.0,
    "model_name": "microsoft/phi-2",
    "datetime": "2024-02-21T12:40:10.263379"
}{
    "rouge1": 7.63,
    "rouge2": 0.0,
    "rougeL": 6.92,
    "rougeLsum": 6.92,
    "R": 4.84,
    "gen_len": 1.0,
    "model_name": "microsoft/phi-2",
    "datetime": "2024-02-21T12:40:57.969247"
}{
    "rouge1": 3.22,
    "rouge2": 0.05,
    "rougeL": 2.7,
    "rougeLsum": 2.65,
    "R": 1.99,
    "gen_len": 1.0,
    "model_name": "microsoft/phi-2",
    "datetime": "2024-02-21T12:44:42.255360"
}{
    "rouge1": 4.42,
    "rouge2": 0.36,
    "rougeL": 3.88,
    "rougeLsum": 3.86,
    "R": 2.89,
    "gen_len": 1.0,
    "model_name": "microsoft/phi-2",
    "datetime": "2024-02-21T12:59:14.309599"
}{
    "rouge1": 3.22,
    "rouge2": 0.05,
    "rougeL": 2.7,
    "rougeLsum": 2.65,
    "R": 1.99,
    "gen_len": 1.0,
    "model_name": "microsoft/phi-2",
    "datetime": "2024-02-21T13:03:43.979592"
}{
    "rouge1": 4.89,
    "rouge2": 1.22,
    "rougeL": 4.43,
    "rougeLsum": 4.49,
    "R": 3.51,
    "gen_len": 1.0,
    "model_name": "microsoft/phi-2",
    "datetime": "2024-02-21T13:20:41.709591"
}{
    "rouge1": 3.22,
    "rouge2": 0.05,
    "rougeL": 2.7,
    "rougeLsum": 2.65,
    "R": 1.99,
    "gen_len": 1.0,
    "model_name": "microsoft/phi-2",
    "datetime": "2024-02-21T13:23:26.476655"
}{
    "rouge1": 4.22,
    "rouge2": 0.2,
    "rougeL": 3.57,
    "rougeLsum": 3.57,
    "R": 2.66,
    "gen_len": 1.0,
    "model_name": "microsoft/phi-2",
    "datetime": "2024-02-21T13:36:13.337313"
}{
    "rouge1": 5.18,
    "rouge2": 1.15,
    "rougeL": 4.8,
    "rougeLsum": 4.72,
    "R": 3.71,
    "gen_len": 1.0,
    "model_name": "microsoft/phi-2",
    "datetime": "2024-02-21T13:54:04.993681"
}{
    "rouge1": 4.22,
    "rouge2": 0.2,
    "rougeL": 3.57,
    "rougeLsum": 3.57,
    "R": 2.66,
    "gen_len": 1.0,
    "model_name": "microsoft/phi-2",
    "datetime": "2024-02-21T14:09:49.566591"
}{
    "rouge1": 5.51,
    "rouge2": 1.25,
    "rougeL": 4.75,
    "rougeLsum": 4.83,
    "R": 3.84,
    "gen_len": 1.0,
    "model_name": "microsoft/phi-2",
    "datetime": "2024-02-21T14:35:33.530920"
}{
    "rouge1": 6.9,
    "rouge2": 1.51,
    "rougeL": 6.16,
    "rougeLsum": 6.13,
    "R": 4.85,
    "gen_len": 1.0,
    "model_name": "llamantino7b_2_question-answering",
    "datetime": "2024-02-21T15:13:09.071011"
}{
    "rouge1": 6.33,
    "rouge2": 1.06,
    "rougeL": 5.5,
    "rougeLsum": 5.53,
    "R": 4.29,
    "gen_len": 1.0,
    "model_name": "llamantino7b_2_question-answering",
    "datetime": "2024-02-21T15:21:47.955388"
}{
    "rouge1": 6.33,
    "rouge2": 1.06,
    "rougeL": 5.5,
    "rougeLsum": 5.53,
    "R": 4.29,
    "gen_len": 1.0,
    "model_name": "llamantino7b_2_question-answering",
    "datetime": "2024-02-21T15:30:13.946596"
}{
    "rouge1": 11.69,
    "rouge2": 4.98,
    "rougeL": 10.66,
    "rougeLsum": 10.8,
    "R": 9.1,
    "gen_len": 1.0,
    "model_name": "llamantino7b_2_question-answering",
    "datetime": "2024-02-21T17:45:28.742907"
}{
    "rouge1": 8.64,
    "rouge2": 3.25,
    "rougeL": 7.89,
    "rougeLsum": 7.85,
    "R": 6.59,
    "gen_len": 1.0,
    "model_name": "llamantino7b_2_question-answering",
    "datetime": "2024-02-21T18:04:34.225422"
}{
    "rouge1": 0.04,
    "rouge2": 0.0,
    "rougeL": 0.04,
    "rougeLsum": 0.04,
    "R": 0.03,
    "gen_len": 1.0,
    "model_name": "llamantino7b_2_question-answering",
    "datetime": "2024-02-21T18:47:39.503828"
}{
    "rouge1": 0.07,
    "rouge2": 0.0,
    "rougeL": 0.08,
    "rougeLsum": 0.08,
    "R": 0.05,
    "gen_len": 1.0,
    "model_name": "llamantino7b_2_question-answering",
    "datetime": "2024-02-21T18:51:15.011413"
}{
    "rouge1": 0.0,
    "rouge2": 0.0,
    "rougeL": 0.0,
    "rougeLsum": 0.0,
    "R": 0.0,
    "gen_len": 1.0,
    "model_name": "llamantino7b_2_question-answering",
    "datetime": "2024-02-21T18:54:47.984752"
}{
    "rouge1": 0.0,
    "rouge2": 0.0,
    "rougeL": 0.0,
    "rougeLsum": 0.0,
    "R": 0.0,
    "gen_len": 1.0,
    "model_name": "llamantino7b_2_question-answering",
    "datetime": "2024-02-21T18:57:37.768137"
}{
    "rouge1": 8.42,
    "rouge2": 1.89,
    "rougeL": 7.59,
    "rougeLsum": 7.4,
    "R": 5.96,
    "gen_len": 1.0,
    "model_name": "llamantino7b_2_question-answering",
    "datetime": "2024-02-21T19:04:18.375776"
}{
    "rouge1": 6.6,
    "rouge2": 1.24,
    "rougeL": 5.88,
    "rougeLsum": 5.67,
    "R": 4.57,
    "gen_len": 1.0,
    "model_name": "llamantino7b_2_question-answering",
    "datetime": "2024-02-21T19:16:57.844643"
}{
    "rouge1": 9.19,
    "rouge2": 3.54,
    "rougeL": 8.02,
    "rougeLsum": 7.97,
    "R": 6.91,
    "gen_len": 1.0,
    "model_name": "llamantino7b_2_question-answering",
    "datetime": "2024-02-21T19:40:29.702886"
}{
    "rouge1": 6.6,
    "rouge2": 1.24,
    "rougeL": 5.88,
    "rougeLsum": 5.67,
    "R": 4.57,
    "gen_len": 1.0,
    "model_name": "llamantino7b_2_question-answering",
    "datetime": "2024-02-21T19:51:13.150902"
}{
    "rouge1": 9.19,
    "rouge2": 3.54,
    "rougeL": 8.02,
    "rougeLsum": 7.97,
    "R": 6.91,
    "gen_len": 1.0,
    "model_name": "llamantino7b_2_question-answering",
    "datetime": "2024-02-21T20:17:32.663715"
}{
    "rouge1": 9.16,
    "rouge2": 3.54,
    "rougeL": 7.99,
    "rougeLsum": 7.93,
    "R": 6.89,
    "gen_len": 1.0,
    "model_name": "llamantino7b_2_question-answering",
    "datetime": "2024-02-21T21:43:13.861105"
}{
    "rouge1": 9.02,
    "rouge2": 2.37,
    "rougeL": 8.24,
    "rougeLsum": 8.23,
    "R": 6.54,
    "gen_len": 1.0,
    "model_name": "llamantino7b_2_BASE_question-answering",
    "datetime": "2024-02-21T21:54:22.853060"
}{
    "rouge1": 9.9,
    "rouge2": 4.32,
    "rougeL": 8.87,
    "rougeLsum": 8.85,
    "R": 7.69,
    "gen_len": 1.0,
    "model_name": "llamantino7b_2_question-answering",
    "datetime": "2024-02-21T22:50:58.663119"
}{
    "rouge1": 9.02,
    "rouge2": 2.37,
    "rougeL": 8.24,
    "rougeLsum": 8.23,
    "R": 6.54,
    "gen_len": 1.0,
    "model_name": "llamantino7b_2_BASE_question-answering",
    "datetime": "2024-02-21T23:02:02.319721"
}{
    "rouge1": 5.36,
    "rouge2": 1.35,
    "rougeL": 5.36,
    "rougeLsum": 5.36,
    "R": 4.02,
    "gen_len": 1.0,
    "model_name": "HuggingFaceH4/zephyr-7b-beta",
    "datetime": "2024-02-22T00:04:17.396881"
}{
    "rouge1": 5.36,
    "rouge2": 1.35,
    "rougeL": 5.36,
    "rougeLsum": 5.36,
    "R": 4.02,
    "gen_len": 1.0,
    "model_name": "HuggingFaceH4/zephyr-7b-beta",
    "datetime": "2024-02-22T00:15:22.204025"
}{
    "rouge1": 11.3,
    "rouge2": 1.25,
    "rougeL": 8.84,
    "rougeLsum": 8.53,
    "R": 7.12,
    "gen_len": 1.0,
    "model_name": "HuggingFaceH4/zephyr-7b-beta",
    "datetime": "2024-02-22T00:16:43.480765"
}{
    "rouge1": 7.96,
    "rouge2": 1.43,
    "rougeL": 6.58,
    "rougeLsum": 6.65,
    "R": 5.32,
    "gen_len": 1.0,
    "model_name": "HuggingFaceH4/zephyr-7b-beta",
    "datetime": "2024-02-22T00:28:11.481791"
}{
    "rouge1": 7.23,
    "rouge2": 1.07,
    "rougeL": 6.29,
    "rougeLsum": 6.27,
    "R": 4.86,
    "gen_len": 1.0,
    "model_name": "lvcalucioli/zephyr-7b-beta_question-answering",
    "datetime": "2024-02-22T00:46:19.877842"
}{
    "rouge1": 7.23,
    "rouge2": 1.07,
    "rougeL": 6.29,
    "rougeLsum": 6.27,
    "R": 4.86,
    "gen_len": 1.0,
    "model_name": "lvcalucioli/zephyr-7b-beta_question-answering",
    "datetime": "2024-02-22T01:07:11.945573"
}{
    "rouge1": 8.32,
    "rouge2": 3.03,
    "rougeL": 7.34,
    "rougeLsum": 7.37,
    "R": 6.23,
    "gen_len": 1.0,
    "model_name": "lvcalucioli/llamantino7b_2_question-answering_question-answering",
    "datetime": "2024-02-22T06:24:19.583481"
}{
    "rouge1": 8.74,
    "rouge2": 1.92,
    "rougeL": 7.82,
    "rougeLsum": 8.11,
    "R": 6.15,
    "gen_len": 1.0,
    "model_name": "llamantino7b_2_question-answering",
    "datetime": "2024-02-22T11:39:59.837681"
}{
    "rouge1": 8.31,
    "rouge2": 2.24,
    "rougeL": 7.48,
    "rougeLsum": 7.71,
    "R": 6.01,
    "gen_len": 1.0,
    "model_name": "llamantino7b_2_question-answering",
    "datetime": "2024-02-22T12:28:04.791671"
}{
    "rouge1": 9.02,
    "rouge2": 2.37,
    "rougeL": 8.24,
    "rougeLsum": 8.23,
    "R": 6.54,
    "gen_len": 1.0,
    "model_name": "llamantino7b_2_question-answering",
    "datetime": "2024-02-22T12:45:57.147106"
}{
    "rouge1": 9.02,
    "rouge2": 2.37,
    "rougeL": 8.24,
    "rougeLsum": 8.23,
    "R": 6.54,
    "gen_len": 1.0,
    "model_name": "llamantino7b_2_question-answering",
    "datetime": "2024-02-22T13:08:05.605761"
}{
    "rouge1": 9.1,
    "rouge2": 2.34,
    "rougeL": 8.17,
    "rougeLsum": 8.22,
    "R": 6.53,
    "gen_len": 1.0,
    "model_name": "llamantino_base",
    "datetime": "2024-02-22T13:12:09.471054"
}{
    "rouge1": 8.96,
    "rouge2": 2.39,
    "rougeL": 8.17,
    "rougeLsum": 8.29,
    "R": 6.5,
    "gen_len": 1.0,
    "model_name": "llamantino_base",
    "datetime": "2024-02-22T13:13:05.170930"
}{
    "rouge1": 8.99,
    "rouge2": 2.35,
    "rougeL": 8.18,
    "rougeLsum": 8.3,
    "R": 6.5,
    "gen_len": 1.0,
    "model_name": "llamantino_base",
    "datetime": "2024-02-22T13:14:25.976242"
}{
    "rouge1": 8.25,
    "rouge2": 2.23,
    "rougeL": 7.52,
    "rougeLsum": 7.73,
    "R": 6.0,
    "gen_len": 1.0,
    "model_name": "llamantino_base",
    "datetime": "2024-02-22T13:32:43.347647"
}{
    "rouge1": 8.02,
    "rouge2": 1.99,
    "rougeL": 7.19,
    "rougeLsum": 7.36,
    "R": 5.73,
    "gen_len": 1.0,
    "model_name": "llamantino_base",
    "datetime": "2024-02-22T14:31:41.498451"
}{
    "rouge1": 8.01,
    "rouge2": 1.96,
    "rougeL": 7.11,
    "rougeLsum": 7.27,
    "R": 5.69,
    "gen_len": 1.0,
    "model_name": "llamantino_base",
    "datetime": "2024-02-22T15:31:27.300661"
}